xiaobanma/API.py
xiaobanma/DialogBox.png
xiaobanma/__init__.py
xiaobanma/abstract.py
xiaobanma/camera.py
xiaobanma/config.py
xiaobanma/constraints.py
xiaobanma/cursor.py
xiaobanma/draw.py
xiaobanma/draw_options.py
xiaobanma/events.py
xiaobanma/facilitate.py
xiaobanma/game_object.py
xiaobanma/music.py
xiaobanma/physics.py
xiaobanma/pymunk_logo_googlecode.png
xiaobanma/screen.py
xiaobanma/settings.py
xiaobanma/simkai.ttf
xiaobanma/simsun.ttc
xiaobanma/sprite.py
xiaobanma/test.py
xiaobanma/textbox.py
xiaobanma/tiledmap.py
xiaobanma/__pycache__/API.cpython-36.pyc
xiaobanma/__pycache__/API.cpython-37.pyc
xiaobanma/__pycache__/__init__.cpython-36.pyc
xiaobanma/__pycache__/__init__.cpython-37.pyc
xiaobanma/__pycache__/abstract.cpython-36.pyc
xiaobanma/__pycache__/camera.cpython-36.pyc
xiaobanma/__pycache__/camera.cpython-37.pyc
xiaobanma/__pycache__/config.cpython-36.pyc
xiaobanma/__pycache__/config.cpython-37.pyc
xiaobanma/__pycache__/constraints.cpython-36.pyc
xiaobanma/__pycache__/constraints.cpython-37.pyc
xiaobanma/__pycache__/cursor.cpython-36.pyc
xiaobanma/__pycache__/draw.cpython-36.pyc
xiaobanma/__pycache__/draw.cpython-37.pyc
xiaobanma/__pycache__/draw_options.cpython-36.pyc
xiaobanma/__pycache__/draw_options.cpython-37.pyc
xiaobanma/__pycache__/events.cpython-36.pyc
xiaobanma/__pycache__/events.cpython-37.pyc
xiaobanma/__pycache__/facilitate.cpython-36.pyc
xiaobanma/__pycache__/facilitate.cpython-37.pyc
xiaobanma/__pycache__/game_object.cpython-36.pyc
xiaobanma/__pycache__/game_object.cpython-37.pyc
xiaobanma/__pycache__/music.cpython-36.pyc
xiaobanma/__pycache__/music.cpython-37.pyc
xiaobanma/__pycache__/physics.cpython-36.pyc
xiaobanma/__pycache__/physics.cpython-37.pyc
xiaobanma/__pycache__/screen.cpython-36.pyc
xiaobanma/__pycache__/screen.cpython-37.pyc
xiaobanma/__pycache__/settings.cpython-36.pyc
xiaobanma/__pycache__/settings.cpython-37.pyc
xiaobanma/__pycache__/sprite.cpython-36.pyc
xiaobanma/__pycache__/sprite.cpython-37.pyc
xiaobanma-2.0.5.dist-info/LICENSE
xiaobanma-2.0.5.dist-info/METADATA
xiaobanma-2.0.5.dist-info/WHEEL
xiaobanma-2.0.5.dist-info/top_level.txt
xiaobanma-2.0.5.dist-info/RECORD
